Metadata-Version: 2.4
Name: fmchisel
Version: 0.1.2
Summary: FMCHISEL is a library which aims at improving LLM training + inference effectiveness and efficiency from an algorithm perspective with quantization, pruning, optimizers, etc.
License: BSD 2-CLAUSE LICENSE
Project-URL: Homepage, https://github.com/linkedin/FMCHISEL
License-File: LICENSE
License-File: NOTICE
Requires-Dist: torch<2.8.0,>=2.6.0
Requires-Dist: transformers<5.0.0,>=4.48.0
Requires-Dist: datasets<5.0.0,>=4.0.0
Requires-Dist: dataclasses_json
Provides-Extra: inference
Requires-Dist: llmcompressor==0.5.1; extra == "inference"
Provides-Extra: train
Requires-Dist: lightning<3.0.0,>=2.3.2; extra == "train"
Requires-Dist: liger-kernel<1.0.0,>=0.5.0; extra == "train"
Provides-Extra: dev
Requires-Dist: matplotlib>=3.7.2; extra == "dev"
Requires-Dist: flake8>=4.0.1.1; extra == "dev"
Requires-Dist: black>=24.4.2; extra == "dev"
Requires-Dist: isort>=5.13.2; extra == "dev"
Requires-Dist: pytest>=7.1.2; extra == "dev"
Requires-Dist: pre-commit; extra == "dev"
Requires-Dist: pytest-xdist; extra == "dev"
Requires-Dist: pytest-rerunfailures; extra == "dev"
Requires-Dist: seaborn; extra == "dev"
Requires-Dist: mkdocs; extra == "dev"
Requires-Dist: mkdocs-material; extra == "dev"
Requires-Dist: llmcompressor==0.5.1; extra == "dev"
Requires-Dist: lightning<3.0.0,>=2.3.2; extra == "dev"
Requires-Dist: liger-kernel<1.0.0,>=0.5.0; extra == "dev"
Provides-Extra: all
Requires-Dist: llmcompressor==0.5.1; extra == "all"
Requires-Dist: lightning<3.0.0,>=2.3.2; extra == "all"
Requires-Dist: liger-kernel<1.0.0,>=0.5.0; extra == "all"
Dynamic: license-file
Dynamic: provides-extra
Dynamic: requires-dist
